setup.py
integration/__init__.py
integration/plugin_spec.py
tryp_nvim.egg-info/PKG-INFO
tryp_nvim.egg-info/SOURCES.txt
tryp_nvim.egg-info/dependency_links.txt
tryp_nvim.egg-info/requires.txt
tryp_nvim.egg-info/top_level.txt
trypnv/__init__.py
trypnv/cmd.py
trypnv/data.py
trypnv/logging.py
trypnv/machine.py
trypnv/nvim.py
trypnv/plugin.py
trypnv/process.py
trypnv/record.py
trypnv/test/__init__.py
trypnv/test/integration.py
trypnv/test/spec.py