Metadata-Version: 1.0
Name: tryp-nvim
Version: 7.3.0
Summary: neovim helpers
Home-page: https://github.com/tek/tryp-nvim
Author: Torsten Schmits
Author-email: torstenschmits@gmail.com
License: MIT
Platform: UNKNOWN
